{"AccountWithUserName":[{"Account":{"ID":3,"ClientId":9,"AccountNumber":2,"Balance":3434,"Status":true,"CardNumber":"","LimitTransfer":0,"LimitPayment":0,"CreatedAt":"0001-01-01T00:00:00Z","UntilAt":"0001-01-01T00:00:00Z"},"Client":{"ID":9,"Name":"furkat","Surname":"kasimov","Login":"furkat","Password":"81dc9bdb52d04dc20036dbd8313ed055","Age":0,"Gender":"","Phone":"004444025","Status":true,"VerifiedAt":"2000-01-01T16:18:24.631199Z"}},{"Account":{"ID":5,"ClientId":9,"AccountNumber":3,"Balance":1213123,"Status":true,"CardNumber":"","LimitTransfer":0,"LimitPayment":0,"CreatedAt":"0001-01-01T00:00:00Z","UntilAt":"0001-01-01T00:00:00Z"},"Client":{"ID":9,"Name":"furkat","Surname":"kasimov","Login":"furkat","Password":"81dc9bdb52d04dc20036dbd8313ed055","Age":0,"Gender":"","Phone":"004444025","Status":true,"VerifiedAt":"2000-01-01T16:18:24.631199Z"}},{"Account":{"ID":1,"ClientId":9,"AccountNumber":1,"Balance":59,"Status":true,"CardNumber":"","LimitTransfer":0,"LimitPayment":0,"CreatedAt":"0001-01-01T00:00:00Z","UntilAt":"0001-01-01T00:00:00Z"},"Client":{"ID":9,"Name":"furkat","Surname":"kasimov","Login":"furkat","Password":"81dc9bdb52d04dc20036dbd8313ed055","Age":0,"Gender":"","Phone":"004444025","Status":true,"VerifiedAt":"2000-01-01T16:18:24.631199Z"}},{"Account":{"ID":6,"ClientId":10,"AccountNumber":4,"Balance":88,"Status":true,"CardNumber":"","LimitTransfer":0,"LimitPayment":0,"CreatedAt":"0001-01-01T00:00:00Z","UntilAt":"0001-01-01T00:00:00Z"},"Client":{"ID":10,"Name":"kasimov","Surname":"kasimov","Login":"kasimov","Password":"81dc9bdb52d04dc20036dbd8313ed055","Age":0,"Gender":"","Phone":"004443445","Status":true,"VerifiedAt":"2000-01-01T16:18:24.631199Z"}}]}